clitree/__init__.py
clitree/tree.py
clitree-0.1.0.dist-info/METADATA
clitree-0.1.0.dist-info/WHEEL
clitree-0.1.0.dist-info/licenses/LICENSE
clitree-0.1.0.dist-info/RECORD
